sysproxy.cp313t-win_amd64.pyd
sysproxy-0.1.7.dist-info/licenses/LICENSE
sysproxy-0.1.7.dist-info/METADATA
sysproxy-0.1.7.dist-info/WHEEL
sysproxy-0.1.7.dist-info/top_level.txt
sysproxy-0.1.7.dist-info/RECORD
