Metadata-Version: 2.1
Name: sysproxy
Version: 0.1.7
Summary: Python bindings for shadowsocks sysproxy utility.
Home-page: https://github.com/LorenEteval/sysproxy
Author: Loren Eteval
Author-email: loren.eteval@proton.me
License: MIT
Platform: UNKNOWN
Classifier: Development Status :: 5 - Production/Stable
Classifier: License :: OSI Approved :: MIT License
Classifier: Intended Audience :: Developers
Classifier: Programming Language :: C++
Classifier: Programming Language :: Python :: 3
Classifier: Programming Language :: Python :: 3 :: Only
Classifier: Programming Language :: Python :: 3.6
Classifier: Programming Language :: Python :: 3.7
Classifier: Programming Language :: Python :: 3.8
Classifier: Programming Language :: Python :: 3.9
Classifier: Programming Language :: Python :: 3.10
Classifier: Programming Language :: Python :: 3.11
Classifier: Programming Language :: Python :: 3.12
Classifier: Programming Language :: Python :: 3.13
Classifier: Operating System :: Microsoft :: Windows
Classifier: Topic :: Internet
Classifier: Topic :: Internet :: Proxy Servers
Requires-Dist: pybind11 <2.13.0
